figures/les2banner.png
figures/verus_logo.png
verus/__init__.py
verus/_version.py
verus/verus.py
verus/clustering/__init__.py
verus/clustering/kmeans.py
verus/clustering/optics.py
verus/data/__init__.py
verus/data/extraction.py
verus/data/timewindow.py
verus/grid/__init__.py
verus/grid/hexagon.py
verus/utils/__init__.py
verus/utils/logger.py
verus/utils/timer.py
verus-1.0.1.dist-info/licenses/LICENSE
verus-1.0.1.dist-info/METADATA
verus-1.0.1.dist-info/WHEEL
verus-1.0.1.dist-info/top_level.txt
verus-1.0.1.dist-info/RECORD
